envserv/__init__.py
envserv/errors.py
envserv/get/base.py
envserv/get/variables.py
envserv/typing/__init__.py
envserv/typing/variable.py
envserv-1.0.7.dist-info/LICENSE
envserv-1.0.7.dist-info/METADATA
envserv-1.0.7.dist-info/WHEEL
envserv-1.0.7.dist-info/top_level.txt
envserv-1.0.7.dist-info/RECORD
