Metadata-Version: 2.2
Name: envserv
Version: 1.0.7
Summary: Environment model
Author-email: txello <txello@inbox.ru>
Project-URL: Homepage, https://github.com/txello/EnvServ
Project-URL: Issues, https://github.com/txello/EnvServ/issues
Classifier: Programming Language :: Python :: 3
Classifier: License :: OSI Approved :: MIT License
Classifier: Operating System :: OS Independent
Requires-Python: >=3.8
License-File: LICENSE
Requires-Dist: python-dotenv>=1.0.1
